cs.adminlanguage-1.1-py3.11-nspkg.pth
cs/adminlanguage/__init__.py
cs/adminlanguage/configure.zcml
cs/adminlanguage/interfaces.py
cs/adminlanguage/messagefactory.py
cs/adminlanguage/negotiator.py
cs/adminlanguage/permissions.zcml
cs/adminlanguage/settings.py
cs/adminlanguage/setuphandlers.py
cs/adminlanguage/testing.py
cs/adminlanguage/locales/README.rst
cs/adminlanguage/locales/__init__.py
cs/adminlanguage/locales/cs.adminlanguage.pot
cs/adminlanguage/locales/update.py
cs/adminlanguage/locales/update.sh
cs/adminlanguage/locales/en/LC_MESSAGES/cs.adminlanguage.po
cs/adminlanguage/profiles/default/browserlayer.xml
cs/adminlanguage/profiles/default/catalog.xml
cs/adminlanguage/profiles/default/controlpanel.xml
cs/adminlanguage/profiles/default/metadata.xml
cs/adminlanguage/profiles/default/registry.xml
cs/adminlanguage/profiles/default/rolemap.xml
cs/adminlanguage/profiles/uninstall/browserlayer.xml
cs/adminlanguage/profiles/uninstall/controlpanel.xml
cs/adminlanguage/profiles/uninstall/registry.xml
cs/adminlanguage/tests/__init__.py
cs/adminlanguage/tests/test_setup.py
cs.adminlanguage-1.1.dist-info/LICENSE.GPL
cs.adminlanguage-1.1.dist-info/LICENSE.rst
cs.adminlanguage-1.1.dist-info/METADATA
cs.adminlanguage-1.1.dist-info/WHEEL
cs.adminlanguage-1.1.dist-info/entry_points.txt
cs.adminlanguage-1.1.dist-info/namespace_packages.txt
cs.adminlanguage-1.1.dist-info/top_level.txt
cs.adminlanguage-1.1.dist-info/RECORD
