Metadata-Version: 2.2
Name: cs.adminlanguage
Version: 1.1
Summary: Addon to set the admin language
Home-page: https://github.com/collective/cs.adminlanguage
Author: Lur Ibargutxi
Author-email: libargutxi@codesyntax.com
License: GPL version 2
Project-URL: PyPI, https://pypi.python.org/pypi/cs.adminlanguage
Project-URL: Source, https://github.com/collective/cs.adminlanguage
Project-URL: Tracker, https://github.com/collective/cs.adminlanguage/issues
Keywords: Python Plone
Classifier: Environment :: Web Environment
Classifier: Framework :: Plone
Classifier: Framework :: Plone :: Addon
Classifier: Framework :: Plone :: 6.0
Classifier: Programming Language :: Python
Classifier: Programming Language :: Python :: 3.10
Classifier: Programming Language :: Python :: 3.11
Classifier: Programming Language :: Python :: 3.12
Classifier: Operating System :: OS Independent
Classifier: License :: OSI Approved :: GNU General Public License v2 (GPLv2)
Classifier: Development Status :: 5 - Production/Stable
Requires-Python: >=3.10
License-File: LICENSE.GPL
License-File: LICENSE.rst
Requires-Dist: setuptools
Requires-Dist: AccessControl
Requires-Dist: plone.app.registry
Requires-Dist: plone.registry
Requires-Dist: plone.z3cform
Requires-Dist: Products.CMFCore
Requires-Dist: Products.CMFPlone
Requires-Dist: Products.GenericSetup
Requires-Dist: zope.component
Requires-Dist: zope.globalrequest
Requires-Dist: zope.i18n
Requires-Dist: zope.i18nmessageid
Requires-Dist: zope.interface
Requires-Dist: zope.publisher
Requires-Dist: zope.schema
Provides-Extra: test
Requires-Dist: plone.app.testing; extra == "test"
Requires-Dist: plone.api; extra == "test"
Requires-Dist: plone.app.contenttypes; extra == "test"
Requires-Dist: plone.app.robotframework[debug]; extra == "test"
Requires-Dist: plone.browserlayer; extra == "test"
Requires-Dist: plone.testing>=5.0.0; extra == "test"
Dynamic: author
Dynamic: author-email
Dynamic: classifier
Dynamic: description
Dynamic: home-page
Dynamic: keywords
Dynamic: license
Dynamic: project-url
Dynamic: provides-extra
Dynamic: requires-dist
Dynamic: requires-python
Dynamic: summary
